pydrivelist/__init__.py
pydrivelist/main.py
pydrivelist/version.py
pydrivelist-0.1.0.dist-info/METADATA
pydrivelist-0.1.0.dist-info/WHEEL
pydrivelist-0.1.0.dist-info/entry_points.txt
pydrivelist-0.1.0.dist-info/top_level.txt
pydrivelist-0.1.0.dist-info/RECORD
