Metadata-Version: 2.1
Name: pydrivelist
Version: 0.1.0
Summary: Python Package for Listing Paths to Drive Identifiers
Home-page: https://atmseminar.org/
Author: Nelson Brown, FAA Human Factors, ANG-E25
Author-email: nelson.brown@faa.gov
License: UNKNOWN
Platform: UNKNOWN
Classifier: Development Status :: 4 - Beta
Classifier: Environment :: Console
Classifier: Operating System :: POSIX :: Linux
Classifier: Intended Audience :: Developers
Classifier: Natural Language :: English
Classifier: License :: CC0 1.0 Universal (CC0 1.0) Public Domain Dedication
Classifier: Programming Language :: Python :: 3.5
Classifier: Programming Language :: Python :: 3.6
Classifier: Programming Language :: Python :: 3.7
Requires-Python: >=3.6
Requires-Dist: PyDrive2 (>=1.10.0)
